src/data_memory.v
`timescale 1ns/1ps
// ============================================================
// data_memory.v — RTL translation of data_memory.dig
//
// .dig implementation:
//   RAMDualPort element (AddrBits=8, Bits=8)
//   256 × 8-bit synchronous dual-port RAM.
//
//   Port A (write port):
//     A_addr  = address[7:0]   — same wire as Port B address
//     A_din   = write_data[7:0]
//     A_we    = mem_write       — asserted in WRITEBACK for STORE
//     A_clk   = clk
//
//   Port B (read port):
//     B_addr  = address[7:0]   — same wire as Port A address
//     B_dout  = read_data[7:0]
//     B_re    = mem_read        — asserted in EXECUTE + WRITEBACK for LOAD
//     B_clk   = clk
//
//   CRITICAL: The single 'address' In port in data_memory.dig
//   connects to BOTH the Port A address input and the Port B
//   address input. Both ports share the same address bus.
//
//   Both ports are synchronous — registered on posedge clk.
//   The read output is registered, so LOAD requires two cycles:
//
//   Two-cycle LOAD sequence:
//     EXECUTE:   mem_read=1; RAMDualPort Port B captures address
//                on this posedge clk
//     WRITEBACK: mem_read=1 held; read_data is now valid;
//                reg_write=1 routes mem_data to register file
//
//   Address source from cpu_core_test.dig:
//     address = {2'b00, imm6[5:0]} — zero-extended to 8-bit
//     Accessible range: 0x00–0x3F (0–63) in v0.3
// ============================================================

module data_memory (
    input  wire       clk,
    input  wire       mem_read,
    input  wire       mem_write,
    input  wire [7:0] address,
    input  wire [7:0] write_data,
    output reg  [7:0] read_data
);

    reg [7:0] memory [0:255];

    integer i;
    initial begin
        for (i = 0; i < 256; i = i + 1)
            memory[i] = 8'h00;
    end

    // ---- Port A: synchronous write --------------------------------
    // ---- Port B: synchronous read (registered output) ------------
    // Both ports share the same address bus, clocked on posedge.
    // This matches RAMDualPort behaviour in Digital exactly:
    // the read output updates on the same rising edge that re is
    // sampled, so read_data is valid in the cycle AFTER mem_read
    // is asserted — i.e. valid in WRITEBACK when asserted in EXECUTE.
    always @(posedge clk) begin
        // Port A — write
        if (mem_write)
            memory[address] <= write_data;

        // Port B — registered read
        // read_data valid one cycle after mem_read asserted
        if (mem_read)
            read_data <= memory[address];
    end

endmodule

src/alu.v
`timescale 1ns/1ps

module alu (
    input  [7:0] a,
    input  [7:0] b,
    input  [3:0] alu_op,
    output reg [7:0] result,
    output reg zero,
    output reg carry,
    output reg negative,
    output reg overflow
);

reg [8:0] temp;

always @(*) begin
    result   = 8'b00000000;
    carry    = 1'b0;
    overflow = 1'b0;
    temp     = 9'b0;

    case (alu_op)
        4'b0001, 4'b1001: begin  // ADD / ADDI (same ALU operation)
            temp     = a + b;
            result   = temp[7:0];
            carry    = temp[8];
            overflow = (a[7] == b[7]) && (result[7] != a[7]);
        end
        4'b0010: begin  // SUB
            temp     = a - b;
            result   = temp[7:0];
            carry    = temp[8];
            overflow = (a[7] != b[7]) && (result[7] != a[7]);
        end
        4'b0011: result = a & b;  // AND
        4'b0100: result = a | b;  // OR
        4'b0101: result = a ^ b;  // XOR
        4'b1000: result = b;      // MOV
        default: result = 8'b00000000;
    endcase

    zero     = (result == 8'b00000000);
    negative = result[7];
end

endmodule

src/reg_file.v
`timescale 1ns/1ps

module reg_file (
    input clk,
    input reg_write,

    input  [2:0] read_reg1,
    input  [2:0] read_reg2,
    input  [2:0] write_reg,

    input  [7:0] write_data,

    output [7:0] read_data1,
    output [7:0] read_data2
);

    // 8 registers of 8 bits
    reg [7:0] registers [0:7];

    // Initialize registers to 0 (required for simulation;
    // for synthesis/FPGA, add synchronous reset logic instead)
    integer i;
    initial begin
        for (i = 0; i < 8; i = i + 1)
            registers[i] = 8'b0;
    end

    // Asynchronous read
    assign read_data1 = registers[read_reg1];
    assign read_data2 = registers[read_reg2];

    // Synchronous write
    always @(posedge clk) begin
        if (reg_write) begin
            registers[write_reg] <= write_data;
        end
    end

endmodule

src/control_unit.v
`timescale 1ns/1ps

module control_unit (
    input clk,
    input reset,
    input [3:0] opcode,
    input zero_flag,
    input negative_flag,
    input overflow_flag,

    output reg pc_enable,
    output reg pc_load,
    output reg ir_load,
    output reg reg_write,
    output reg [3:0] alu_op,
    output reg alu_src,
    output reg mem_read,
    output reg mem_write
);

    reg [1:0] state;
    reg [3:0] alu_op_latched;
    reg       alu_src_latched;
    reg [3:0] alu_op_exec;
    reg       alu_src_exec;

    localparam FETCH     = 2'b00;
    localparam DECODE    = 2'b01;
    localparam EXECUTE   = 2'b10;
    localparam WRITEBACK = 2'b11;

    // ALU control decode
    always @(*) begin
        alu_op_exec  = 4'b0000;
        alu_src_exec = 1'b0;

        if (opcode == 4'b1011 ||  // BEQ
            opcode == 4'b1100 ||  // BNE
            opcode == 4'b1101) begin // BLT
            alu_op_exec  = 4'b0010;  // SUB for comparison
            alu_src_exec = 1'b0;
        end else begin
            alu_op_exec = opcode;
            if (opcode == 4'b1001) // ADDI
                alu_src_exec = 1'b1;
        end
    end

    // FSM state transition
    always @(posedge clk) begin
        if (reset) begin
            state           <= FETCH;
            alu_op_latched  <= 4'b0000;
            alu_src_latched <= 1'b0;
        end else begin
            if (state == EXECUTE) begin
                alu_op_latched  <= alu_op_exec;
                alu_src_latched <= alu_src_exec;
            end
            state <= state + 1;
        end
    end

    // Control signals (combinational)
    always @(*) begin
        pc_enable = 0;
        pc_load   = 0;
        ir_load   = 0;
        reg_write = 0;
        alu_op    = 4'b0000;
        alu_src   = 0;
        mem_read  = 0;
        mem_write = 0;

        case (state)
            FETCH: begin
                pc_enable = 1;
                ir_load   = 1;
            end

            EXECUTE: begin
                alu_op  = alu_op_exec;
                alu_src = alu_src_exec;
                if (opcode == 4'b0110)
                    mem_read = 1;
            end

            WRITEBACK: begin
                alu_op  = alu_op_latched;
                alu_src = alu_src_latched;

                case (opcode)
                    4'b0001, 4'b0010, 4'b0011,
                    4'b0100, 4'b0101, 4'b1000, 4'b1001:
                        reg_write = 1;  // ADD,SUB,AND,OR,XOR,MOV,ADDI

                    4'b0110: begin
                        mem_read  = 1;
                        reg_write = 1;
                    end

                    4'b0111: mem_write = 1;

                    4'b1010: pc_load = 1;  // JMP

                    4'b1011:                // BEQ
                        if (zero_flag)
                            pc_load = 1;

                    4'b1100:                // BNE
                        if (!zero_flag)
                            pc_load = 1;

                    4'b1101:                // BLT
                        if (negative_flag ^ overflow_flag)
                            pc_load = 1;
                endcase
            end
        endcase
    end

endmodule

src/decoder.v
`timescale 1ns/1ps
module decoder (
    input  [15:0] instruction_in,
    output [3:0] opcode,
    output [2:0] rd,
    output [2:0] rs,
    output [5:0] imm6
);
    assign opcode = instruction_in[15:12];
    assign rd     = instruction_in[11:9];
    assign rs     = instruction_in[8:6];
    assign imm6   = instruction_in[5:0];
endmodule

src/instruction_register.v
`timescale 1ns/1ps

module instruction_register (
    input clk,
    input reset,
    input ir_load,
    input [15:0] instruction_in,
    output reg [15:0] instruction_out
);

always @(posedge clk) begin
    if (reset)
        instruction_out <= 16'b0;
    else if (ir_load)
        instruction_out <= instruction_in;
end

endmodule

src/instruction_memory.v
`timescale 1ns/1ps

// ============================================================
// Instruction Memory (ROM)
// 256 x 16-bit words, asynchronous read
// ============================================================
// v1.2:
//   - Loop now uses SUB R6, R7 (R7=1) to decrement R6 each iteration
//     and BNE R6, R0 to branch back while R6 != 0.
//   - Loop: R6 = 5, R7 = 1, LOOP: R6 = R6 - R7, BNE R6, R0, -2
//   - NOP sentinel at end of program for clean simulation stop.
// ============================================================

module instruction_memory (
    input  [15:0] address,
    output [15:0] instruction
);

    reg [15:0] memory [0:255];

    integer i;
    initial begin
        // Zero out all memory first
        for (i = 0; i < 256; i = i + 1)
            memory[i] = 16'b0000_000_000_000000; // NOP

        // ---------------------------------------------------------
        // Program: demonstrates ADDI, BEQ (taken), STORE, LOAD,
        // SUB, and a finite BNE countdown loop.
        // ---------------------------------------------------------

        // R1 = 5
        memory[0] = 16'b1001_001_000_000101;  // ADDI R1, 5

        // R2 = 5
        memory[1] = 16'b1001_010_000_000101;  // ADDI R2, 5

        // BEQ R1, R2, +1  (skip memory[3])
        memory[2] = 16'b1011_001_010_000001;

        // SKIPPED
        memory[3] = 16'b1001_011_000_000001;  // ADDI R3, 1

        // R4 = 9
        memory[4] = 16'b1001_100_000_001001;  // ADDI R4, 9

        // STORE R4 → MEM[10]
        memory[5] = 16'b0111_100_000_001010;

        // LOAD MEM[10] → R5
        memory[6] = 16'b0110_101_000_001010;

        // R6 = 5  (loop counter, small positive value)
        memory[7] = 16'b1001_110_000_000101;  // ADDI R6, 5

        // R7 = 1  (decrement step)
        memory[8] = 16'b1001_111_000_000001;  // ADDI R7, 1

        // LOOP START (PC=9): R6 = R6 - R7
        memory[9] = 16'b0010_110_111_000000;  // SUB R6, R7

        // BNE R6, R0, -2  → if R6 != 0, go back to memory[9]
        // PC after fetch = 11, offset = -2, target = 11 + (-2) = 9
        memory[10] = 16'b1100_110_000_111110; // BNE R6, R0, -2

        // Loop exits here — R6 == 0
        memory[11] = 16'b0000_000_000_000000; // NOP

    end

    // Asynchronous read (only lower 8 bits used for 256-word space)
    assign instruction = memory[address[7:0]];

endmodule

src/program_counter.v
`timescale 1ns/1ps

module program_counter (
    input clk,
    input reset,
    input pc_enable,
    input pc_load,
    input [15:0] pc_in,
    output reg [15:0] pc_out
);

always @(posedge clk) begin
    if (reset)
        pc_out <= 16'b0;
    else if (pc_load)
        pc_out <= pc_in;
    else if (pc_enable)
        pc_out <= pc_out + 16'd1;
end

endmodule

src/fetch_unit.v
`timescale 1ns/1ps

module fetch_unit (

    input clk,
    input reset,

    // PC control
    input pc_enable,
    input pc_load,
    input [15:0] pc_in,

    // IR control
    input ir_load,

    // Outputs
    output [15:0] instruction_out,
    output [15:0] pc_out
);

    wire [15:0] instruction_from_mem;

    // Program Counter
    program_counter pc (
        .clk(clk),
        .reset(reset),
        .pc_enable(pc_enable),
        .pc_load(pc_load),
        .pc_in(pc_in),
        .pc_out(pc_out)
    );

    // Instruction Memory
    instruction_memory imem (
        .address(pc_out),
        .instruction(instruction_from_mem)
    );

    // Instruction Register
    instruction_register ir (
        .clk(clk),
        .reset(reset),
        .ir_load(ir_load),
        .instruction_in(instruction_from_mem),
        .instruction_out(instruction_out)
    );

endmodule

src/cpu_core.v
`timescale 1ns/1ps

module cpu_core (
    input clk,
    input reset
);

    // FETCH
    wire [15:0] instruction;
    wire [15:0] pc_out;

    wire pc_enable;
    wire pc_load;
    wire ir_load;

    // Signed branch offset
    wire [15:0] signed_offset;
    assign signed_offset = {{10{imm6[5]}}, imm6};

    wire [15:0] branch_target;
    assign branch_target = pc_out + signed_offset;

    fetch_unit fetch (
        .clk(clk),
        .reset(reset),
        .pc_enable(pc_enable),
        .pc_load(pc_load),
        .pc_in(branch_target),
        .ir_load(ir_load),
        .instruction_out(instruction),
        .pc_out(pc_out)
    );

    // DECODE
    wire [3:0] opcode;
    wire [2:0] rd;
    wire [2:0] rs;
    wire [5:0] imm6;

    decoder dec (
        .instruction_in(instruction),
        .opcode(opcode),
        .rd(rd),
        .rs(rs),
        .imm6(imm6)
    );

    // CONTROL
    wire reg_write;
    wire [3:0] alu_op;
    wire alu_src;
    wire mem_read;
    wire mem_write;

    wire zero, carry, negative, overflow;

    control_unit ctrl (
        .clk(clk),
        .reset(reset),
        .opcode(opcode),
        .zero_flag(zero),
        .negative_flag(negative),
        .overflow_flag(overflow),
        .pc_enable(pc_enable),
        .pc_load(pc_load),
        .ir_load(ir_load),
        .reg_write(reg_write),
        .alu_op(alu_op),
        .alu_src(alu_src),
        .mem_read(mem_read),
        .mem_write(mem_write)
    );

    // REGISTER FILE
    wire [7:0] reg_data1;
    wire [7:0] reg_data2;
    wire [7:0] write_data;

    reg_file rf (
        .clk(clk),
        .reg_write(reg_write),
        .read_reg1(rd),
        .read_reg2(rs),
        .write_reg(rd),
        .write_data(write_data),
        .read_data1(reg_data1),
        .read_data2(reg_data2)
    );

    // ALU
    wire [7:0] alu_input_b;
    wire [7:0] alu_result;

    assign alu_input_b = (alu_src) ? {2'b00, imm6} : reg_data2;

    alu alu_unit (
        .a(reg_data1),
        .b(alu_input_b),
        .alu_op(alu_op),
        .result(alu_result),
        .zero(zero),
        .carry(carry),
        .negative(negative),
        .overflow(overflow)
    );

    // DATA MEMORY
    wire [7:0] mem_data;

    data_memory dm (
        .clk(clk),
        .mem_read(mem_read),
        .mem_write(mem_write),
        .address({2'b00, imm6}),
        .write_data(reg_data1),
        .read_data(mem_data)
    );

    // WRITEBACK MUX
    assign write_data = (mem_read) ? mem_data : alu_result;

endmodule

tb/cpu_core_tb.v
`timescale 1ns/1ps

// ============================================================
// CPU Core Testbench
// ============================================================
// FIXES v0.3:
//   - Timeout reduced to #3000 — finite loop runs ~6 iterations
//     (R6: 5→4→3→2→1→0→-1 exits) so simulation now terminates
//     naturally rather than running forever.
//   - Added $stop (after $finish) to guarantee simulator exits.
//   - WB display uses $time for precise timing correlation with VCD.
// ============================================================

module cpu_core_tb;

    reg clk;
    reg reset;

    cpu_core uut (
        .clk   (clk),
        .reset (reset)
    );

    // Clock: 10ns period
    initial begin
        clk = 0;
        forever #5 clk = ~clk;
    end

    initial begin
        $dumpfile("cpu_dump.vcd");
        $dumpvars(0, cpu_core_tb);

        reset = 1;
        #10;
        reset = 0;

        // Finite loop runs 6 iterations × 4 cycles × 10ns = 240ns
        // Full program ~12 instructions + 6 loop iters = ~18 × 40ns = 720ns
        // Give generous headroom: 3000ns
        #3000;

        $display("\n=== Simulation complete (timeout) at time %0t ns ===", $time);
        $display("Final register state:");
        $display("  R0=%0d  R1=%0d  R2=%0d  R3=%0d",
            uut.rf.registers[0], uut.rf.registers[1],
            uut.rf.registers[2], uut.rf.registers[3]);
        $display("  R4=%0d  R5=%0d  R6=%0d  R7=%0d",
            uut.rf.registers[4], uut.rf.registers[5],
            uut.rf.registers[6], uut.rf.registers[7]);
        $display("  PC=%0d", uut.pc_out);
        $finish;
    end

    // --------------------------------------------------------
    // Per-instruction display: fires at end of each WRITEBACK
    // Shows register state AFTER writeback completes.
    // --------------------------------------------------------
    // NOP sentinel detection: stop after first NOP at PC >= 11
    always @(posedge clk) begin
        if (!reset && uut.ctrl.state == 2'b11) begin
            $display("t=%0t  WB  PC=%02d  op=%b  R0=%0d R1=%0d R2=%0d R3=%0d R4=%0d R5=%0d R6=%0d R7=%0d",
                $time, uut.pc_out, uut.opcode,
                uut.rf.registers[0], uut.rf.registers[1],
                uut.rf.registers[2], uut.rf.registers[3],
                uut.rf.registers[4], uut.rf.registers[5],
                uut.rf.registers[6], uut.rf.registers[7]);

            // Detect NOP sentinel at END (PC >= 12 means NOP at 11 was executed)
            if (uut.opcode == 4'b0000 && uut.pc_out >= 12) begin
                $display("\n=== NOP sentinel reached — program complete ===");
                $display("Final register state:");
                $display("  R0=%0d  R1=%0d  R2=%0d  R3=%0d",
                    uut.rf.registers[0], uut.rf.registers[1],
                    uut.rf.registers[2], uut.rf.registers[3]);
                $display("  R4=%0d  R5=%0d  R6=%0d  R7=%0d",
                    uut.rf.registers[4], uut.rf.registers[5],
                    uut.rf.registers[6], uut.rf.registers[7]);
                $display("  PC=%0d", uut.pc_out);
                $finish;
            end
        end
    end

endmodule

cpu_dump.vcd
$date
	Thu Feb 26 07:17:04 2026
$end
$version
	Icarus Verilog
$end
$timescale
	1ps
$end
$scope module cpu_core_tb $end
$var reg 1 ! clk $end
$var reg 1 " reset $end
$scope module uut $end
$var wire 1 ! clk $end
$var wire 1 " reset $end
$var wire 1 # zero $end
$var wire 8 $ write_data [7:0] $end
$var wire 16 % signed_offset [15:0] $end
$var wire 3 & rs [2:0] $end
$var wire 1 ' reg_write $end
$var wire 8 ( reg_data2 [7:0] $end
$var wire 8 ) reg_data1 [7:0] $end
$var wire 3 * rd [2:0] $end
$var wire 16 + pc_out [15:0] $end
$var wire 1 , pc_load $end
$var wire 1 - pc_enable $end
$var wire 1 . overflow $end
$var wire 4 / opcode [3:0] $end
$var wire 1 0 negative $end
$var wire 1 1 mem_write $end
$var wire 1 2 mem_read $end
$var wire 8 3 mem_data [7:0] $end
$var wire 1 4 ir_load $end
$var wire 16 5 instruction [15:0] $end
$var wire 6 6 imm6 [5:0] $end
$var wire 1 7 carry $end
$var wire 16 8 branch_target [15:0] $end
$var wire 1 9 alu_src $end
$var wire 8 : alu_result [7:0] $end
$var wire 4 ; alu_op [3:0] $end
$var wire 8 < alu_input_b [7:0] $end
$scope module alu_unit $end
$var wire 8 = b [7:0] $end
$var wire 4 > alu_op [3:0] $end
$var wire 8 ? a [7:0] $end
$var reg 1 7 carry $end
$var reg 1 0 negative $end
$var reg 1 . overflow $end
$var reg 8 @ result [7:0] $end
$var reg 9 A temp [8:0] $end
$var reg 1 # zero $end
$upscope $end
$scope module ctrl $end
$var wire 1 ! clk $end
$var wire 1 0 negative_flag $end
$var wire 1 . overflow_flag $end
$var wire 1 " reset $end
$var wire 1 # zero_flag $end
$var wire 4 B opcode [3:0] $end
$var reg 4 C alu_op [3:0] $end
$var reg 4 D alu_op_exec [3:0] $end
$var reg 4 E alu_op_latched [3:0] $end
$var reg 1 9 alu_src $end
$var reg 1 F alu_src_exec $end
$var reg 1 G alu_src_latched $end
$var reg 1 4 ir_load $end
$var reg 1 2 mem_read $end
$var reg 1 1 mem_write $end
$var reg 1 - pc_enable $end
$var reg 1 , pc_load $end
$var reg 1 ' reg_write $end
$var reg 2 H state [1:0] $end
$upscope $end
$scope module dec $end
$var wire 3 I rs [2:0] $end
$var wire 3 J rd [2:0] $end
$var wire 4 K opcode [3:0] $end
$var wire 16 L instruction_in [15:0] $end
$var wire 6 M imm6 [5:0] $end
$upscope $end
$scope module dm $end
$var wire 8 N address [7:0] $end
$var wire 1 ! clk $end
$var wire 1 2 mem_read $end
$var wire 1 1 mem_write $end
$var wire 8 O write_data [7:0] $end
$var reg 8 P read_data [7:0] $end
$var integer 32 Q i [31:0] $end
$upscope $end
$scope module fetch $end
$var wire 1 ! clk $end
$var wire 1 4 ir_load $end
$var wire 1 - pc_enable $end
$var wire 16 R pc_in [15:0] $end
$var wire 1 , pc_load $end
$var wire 1 " reset $end
$var wire 16 S pc_out [15:0] $end
$var wire 16 T instruction_out [15:0] $end
$var wire 16 U instruction_from_mem [15:0] $end
$scope module imem $end
$var wire 16 V instruction [15:0] $end
$var wire 16 W address [15:0] $end
$var integer 32 X i [31:0] $end
$upscope $end
$scope module ir $end
$var wire 1 ! clk $end
$var wire 16 Y instruction_in [15:0] $end
$var wire 1 4 ir_load $end
$var wire 1 " reset $end
$var reg 16 Z instruction_out [15:0] $end
$upscope $end
$scope module pc $end
$var wire 1 ! clk $end
$var wire 1 - pc_enable $end
$var wire 16 [ pc_in [15:0] $end
$var wire 1 , pc_load $end
$var wire 1 " reset $end
$var reg 16 \ pc_out [15:0] $end
$upscope $end
$upscope $end
$scope module rf $end
$var wire 1 ! clk $end
$var wire 8 ] read_data1 [7:0] $end
$var wire 8 ^ read_data2 [7:0] $end
$var wire 3 _ read_reg1 [2:0] $end
$var wire 3 ` read_reg2 [2:0] $end
$var wire 1 ' reg_write $end
$var wire 8 a write_data [7:0] $end
$var wire 3 b write_reg [2:0] $end
$var integer 32 c i [31:0] $end
$upscope $end
$upscope $end
$upscope $end
$enddefinitions $end
#0
$dumpvars
b1000 c
bx b
bx a
bx `
bx _
bx ^
bx ]
bx \
bx [
bx Z
bx Y
b100000000 X
bx W
bx V
bx U
bx T
bx S
bx R
b100000000 Q
bx P
bx O
b0xxxxxx N
bx M
bx L
bx K
bx J
bx I
bx H
xG
xF
bx E
bx D
bx C
bx B
bx A
bx @
bx ?
bx >
bx =
bx <
bx ;
bx :
x9
bx 8
x7
bx 6
bx 5
x4
bx 3
x2
x1
x0
bx /
x.
x-
x,
bx +
bx *
bx )
bx (
x'
bx &
bx %
bx $
x#
1"
0!
$end
#5000
b0 8
b0 R
b0 [
0F
b0 D
b0 $
b0 a
b0 <
b0 =
00
1#
b0 A
0.
07
b0 :
b0 @
b1001001000000101 U
b1001001000000101 V
b1001001000000101 Y
b0 N
b0 %
b0 6
b0 M
b0 (
b0 ^
b0 &
b0 I
b0 `
b0 )
b0 ?
b0 O
b0 ]
b0 *
b0 J
b0 _
b0 b
b0 /
b0 B
b0 K
01
02
09
b0 ;
b0 >
b0 C
0'
14
0,
1-
b0 +
b0 S
b0 W
b0 \
b0 5
b0 L
b0 T
b0 Z
0G
b0 E
b0 H
1!
#10000
0!
0"
#15000
1F
b1001 D
04
0-
b101 N
b101 %
b101 6
b101 M
b1 *
b1 J
b1 _
b1 b
b1001 /
b1001 B
b1001 K
b1001010000000101 U
b1001010000000101 V
b1001010000000101 Y
b1 H
b1001001000000101 5
b1001001000000101 L
b1001001000000101 T
b1001001000000101 Z
b110 8
b110 R
b110 [
b1 +
b1 S
b1 W
b1 \
1!
#20000
0!
#25000
b101 $
b101 a
0#
b101 :
b101 @
b101 A
b101 <
b101 =
19
b1001 ;
b1001 >
b1001 C
b10 H
1!
#30000
0!
#35000
b101 A
b101 :
b101 @
1'
19
b1001 ;
b1001 >
b1001 C
b11 H
1G
b1001 E
1!
#40000
0!
#45000
b0 <
b0 =
1#
b0 $
b0 a
14
1-
09
b0 ;
b0 >
b0 C
0'
b0 A
b0 :
b0 @
b0 H
b101 )
b101 ?
b101 O
b101 ]
1!
#50000
0!
#55000
04
0-
b0 )
b0 ?
b0 O
b0 ]
b10 *
b10 J
b10 _
b10 b
b1011001010000001 U
b1011001010000001 V
b1011001010000001 Y
b1 H
b1001010000000101 5
b1001010000000101 L
b1001010000000101 T
b1001010000000101 Z
b111 8
b111 R
b111 [
b10 +
b10 S
b10 W
b10 \
1!
#60000
0!
#65000
b101 $
b101 a
0#
b101 :
b101 @
b101 A
b101 <
b101 =
19
b1001 ;
b1001 >
b1001 C
b10 H
1!
#70000
0!
#75000
b101 A
b101 :
b101 @
1'
19
b1001 ;
b1001 >
b1001 C
b11 H
1!
#80000
0!
#85000
b0 <
b0 =
1#
b0 $
b0 a
14
1-
09
b0 ;
b0 >
b0 C
0'
b0 A
b0 :
b0 @
b0 H
b101 )
b101 ?
b101 O
b101 ]
1!
#90000
0!
#95000
b101 <
b101 =
0F
b10 D
04
0-
b1 N
b1 %
b1 6
b1 M
b101 (
b101 ^
b10 &
b10 I
b10 `
b1 *
b1 J
b1 _
b1 b
b1011 /
b1011 B
b1011 K
b1001011000000001 U
b1001011000000001 V
b1001011000000001 Y
b1 H
b1011001010000001 5
b1011001010000001 L
b1011001010000001 T
b1011001010000001 Z
b100 8
b100 R
b100 [
b11 +
b11 S
b11 W
b11 \
1!
#100000
0!
#105000
b10 ;
b10 >
b10 C
b10 H
1!
#110000
0!
#115000
1,
b10 ;
b10 >
b10 C
b11 H
0G
b10 E
1!
#120000
0!
#125000
b1001100000001001 U
b1001100000001001 V
b1001100000001001 Y
14
1-
b0 ;
b0 >
b0 C
0,
b101 8
b101 R
b101 [
b100 +
b100 S
b100 W
b100 \
b0 H
1!
#130000
0!
#135000
b0 <
b0 =
1F
b1001 D
04
0-
b1001 N
b1001 %
b1001 6
b1001 M
b0 (
b0 ^
b0 &
b0 I
b0 `
b0 )
b0 ?
b0 O
b0 ]
b100 *
b100 J
b100 _
b100 b
b1001 /
b1001 B
b1001 K
b111100000001010 U
b111100000001010 V
b111100000001010 Y
b1 H
b1001100000001001 5
b1001100000001001 L
b1001100000001001 T
b1001100000001001 Z
b1110 8
b1110 R
b1110 [
b101 +
b101 S
b101 W
b101 \
1!
#140000
0!
#145000
b1001 $
b1001 a
0#
b1001 :
b1001 @
b1001 A
b1001 <
b1001 =
19
b1001 ;
b1001 >
b1001 C
b10 H
1!
#150000
0!
#155000
b1001 A
b1001 :
b1001 @
1'
19
b1001 ;
b1001 >
b1001 C
b11 H
1G
b1001 E
1!
#160000
0!
#165000
b0 <
b0 =
1#
b0 $
b0 a
14
1-
09
b0 ;
b0 >
b0 C
0'
b0 A
b0 :
b0 @
b0 H
b1001 )
b1001 ?
b1001 O
b1001 ]
1!
#170000
0!
#175000
0F
b111 D
04
0-
b1010 N
b1010 %
b1010 6
b1010 M
b111 /
b111 B
b111 K
b110101000001010 U
b110101000001010 V
b110101000001010 Y
b1 H
b111100000001010 5
b111100000001010 L
b111100000001010 T
b111100000001010 Z
b10000 8
b10000 R
b10000 [
b110 +
b110 S
b110 W
b110 \
1!
#180000
0!
#185000
b111 ;
b111 >
b111 C
b10 H
1!
#190000
0!
#195000
11
b111 ;
b111 >
b111 C
b11 H
0G
b111 E
1!
#200000
0!
#205000
14
1-
01
b0 ;
b0 >
b0 C
b0 H
1!
#210000
0!
#215000
b110 D
04
0-
b0 )
b0 ?
b0 O
b0 ]
b101 *
b101 J
b101 _
b101 b
b110 /
b110 B
b110 K
b1001110000000101 U
b1001110000000101 V
b1001110000000101 Y
b1 H
b110101000001010 5
b110101000001010 L
b110101000001010 T
b110101000001010 Z
b10001 8
b10001 R
b10001 [
b111 +
b111 S
b111 W
b111 \
1!
#220000
0!
#225000
bx $
bx a
12
b110 ;
b110 >
b110 C
b10 H
1!
#230000
0!
#235000
b1001 $
b1001 a
1'
12
b110 ;
b110 >
b110 C
b1001 3
b1001 P
b11 H
b110 E
1!
#240000
0!
#245000
b0 $
b0 a
14
1-
02
b0 ;
b0 >
b0 C
0'
b0 H
b1001 )
b1001 ?
b1001 O
b1001 ]
1!
#250000
0!
#255000
1F
b1001 D
04
0-
b101 N
b101 %
b101 6
b101 M
b0 )
b0 ?
b0 O
b0 ]
b110 *
b110 J
b110 _
b110 b
b1001 /
b1001 B
b1001 K
b1001111000000001 U
b1001111000000001 V
b1001111000000001 Y
b1 H
b1001110000000101 5
b1001110000000101 L
b1001110000000101 T
b1001110000000101 Z
b1101 8
b1101 R
b1101 [
b1000 +
b1000 S
b1000 W
b1000 \
1!
#260000
0!
#265000
b101 $
b101 a
0#
b101 :
b101 @
b101 A
b101 <
b101 =
19
b1001 ;
b1001 >
b1001 C
b10 H
1!
#270000
0!
#275000
b101 A
b101 :
b101 @
1'
19
b1001 ;
b1001 >
b1001 C
b11 H
1G
b1001 E
1!
#280000
0!
#285000
b0 <
b0 =
1#
b0 $
b0 a
14
1-
09
b0 ;
b0 >
b0 C
0'
b0 A
b0 :
b0 @
b0 H
b101 )
b101 ?
b101 O
b101 ]
1!
#290000
0!
#295000
04
0-
b1 N
b1 %
b1 6
b1 M
b0 )
b0 ?
b0 O
b0 ]
b111 *
b111 J
b111 _
b111 b
b10110111000000 U
b10110111000000 V
b10110111000000 Y
b1 H
b1001111000000001 5
b1001111000000001 L
b1001111000000001 T
b1001111000000001 Z
b1010 8
b1010 R
b1010 [
b1001 +
b1001 S
b1001 W
b1001 \
1!
#300000
0!
#305000
b1 $
b1 a
0#
b1 :
b1 @
b1 A
b1 <
b1 =
19
b1001 ;
b1001 >
b1001 C
b10 H
1!
#310000
0!
#315000
b1 A
b1 :
b1 @
1'
19
b1001 ;
b1001 >
b1001 C
b11 H
1!
#320000
0!
#325000
b0 <
b0 =
1#
b0 $
b0 a
14
1-
09
b0 ;
b0 >
b0 C
0'
b0 A
b0 :
b0 @
b0 H
b1 )
b1 ?
b1 O
b1 ]
1!
#330000
0!
#335000
b1 <
b1 =
0F
b10 D
04
0-
b0 N
b0 %
b0 6
b0 M
b1 (
b1 ^
b111 &
b111 I
b111 `
b101 )
b101 ?
b101 O
b101 ]
b110 *
b110 J
b110 _
b110 b
b10 /
b10 B
b10 K
b1100110000111110 U
b1100110000111110 V
b1100110000111110 Y
b1 H
b10110111000000 5
b10110111000000 L
b10110111000000 T
b10110111000000 Z
b1010 8
b1010 R
b1010 [
b1010 +
b1010 S
b1010 W
b1010 \
1!
#340000
0!
#345000
b100 $
b100 a
0#
b100 :
b100 @
b100 A
b10 ;
b10 >
b10 C
b10 H
1!
#350000
0!
#355000
b100 A
b100 :
b100 @
1'
b10 ;
b10 >
b10 C
b11 H
0G
b10 E
1!
#360000
0!
#365000
1#
b0 $
b0 a
14
1-
b0 ;
b0 >
b0 C
0'
b0 A
b0 :
b0 @
b0 H
b100 )
b100 ?
b100 O
b100 ]
1!
#370000
0!
#375000
b0 <
b0 =
b10 D
04
0-
b111110 N
b1111111111111110 %
b111110 6
b111110 M
b0 (
b0 ^
b0 &
b0 I
b0 `
b1100 /
b1100 B
b1100 K
b0 U
b0 V
b0 Y
b1 H
b1100110000111110 5
b1100110000111110 L
b1100110000111110 T
b1100110000111110 Z
b1001 8
b1001 R
b1001 [
b1011 +
b1011 S
b1011 W
b1011 \
1!
#380000
0!
#385000
b100 $
b100 a
0#
b100 :
b100 @
b100 A
b10 ;
b10 >
b10 C
b10 H
1!
#390000
0!
#395000
b100 A
b100 :
b100 @
1,
b10 ;
b10 >
b10 C
b11 H
1!
#400000
0!
#405000
b0 $
b0 a
1#
b0 A
b0 :
b0 @
b10110111000000 U
b10110111000000 V
b10110111000000 Y
14
1-
b0 ;
b0 >
b0 C
0,
b111 8
b111 R
b111 [
b1001 +
b1001 S
b1001 W
b1001 \
b0 H
1!
#410000
0!
#415000
b1 <
b1 =
b10 D
04
0-
b0 N
b0 %
b0 6
b0 M
b1 (
b1 ^
b111 &
b111 I
b111 `
b10 /
b10 B
b10 K
b1100110000111110 U
b1100110000111110 V
b1100110000111110 Y
b1 H
b10110111000000 5
b10110111000000 L
b10110111000000 T
b10110111000000 Z
b1010 8
b1010 R
b1010 [
b1010 +
b1010 S
b1010 W
b1010 \
1!
#420000
0!
#425000
b11 $
b11 a
0#
b11 :
b11 @
b11 A
b10 ;
b10 >
b10 C
b10 H
1!
#430000
0!
#435000
b11 A
b11 :
b11 @
1'
b10 ;
b10 >
b10 C
b11 H
1!
#440000
0!
